ns_stitchclient/__init__.py
ns_stitchclient/client.py
ns_stitchclient/transit/__init__.py
ns_stitchclient/transit/class_hash.py
ns_stitchclient/transit/constants.py
ns_stitchclient/transit/decoder.py
ns_stitchclient/transit/helpers.py
ns_stitchclient/transit/pyversion.py
ns_stitchclient/transit/read_handlers.py
ns_stitchclient/transit/reader.py
ns_stitchclient/transit/rolling_cache.py
ns_stitchclient/transit/sosjson.py
ns_stitchclient/transit/transit_types.py
ns_stitchclient/transit/write_handlers.py
ns_stitchclient/transit/writer.py
ns_stitchclient-0.9.3.post1.dist-info/LICENSE
ns_stitchclient-0.9.3.post1.dist-info/WHEEL
ns_stitchclient-0.9.3.post1.dist-info/METADATA
ns_stitchclient-0.9.3.post1.dist-info/RECORD
